lapyrinth/__init__.py
lapyrinth/lapyrinth.py
lapyrinth/lapyrinth.pyi
lapyrinth/pathfinders.py
lapyrinth/pathfinders.pyi
lapyrinth/recursive_maze.py
lapyrinth-1.15.0.dist-info/LICENSE
lapyrinth-1.15.0.dist-info/METADATA
lapyrinth-1.15.0.dist-info/WHEEL
lapyrinth-1.15.0.dist-info/top_level.txt
lapyrinth-1.15.0.dist-info/RECORD
